{
  "tracks": [
    {
      "uri": "spotify:track:4WGLZkJcYraCW4r5LAYiNk",
      "duration_ms": 62853,
      "isrc": "",
      "artists_id": [
        "5k3NfhEeZHpouIGDpjKOPo",
        "08rPF2TyeladptG6Z2pYEe"
      ],
      "artists_name": [
        "Shiro SAGISU",
        "Akira Ifukube"
      ]
    },
    {
      "uri": "spotify:track:4WGXebBwTg4heGct5WHvAv",
      "duration_ms": 242833,
      "isrc": "",
      "artists_id": [
        "53YLHx1OfHgQ18JpRV5Bi5"
      ],
      "artists_name": [
        "Organic Call"
      ]
    },
    {
      "uri": "spotify:track:4WMMpXrOFQIOQqVsOBRe7X",
      "duration_ms": 212157,
      "isrc": "",
      "artists_id": [
        "3eOyGULyH8dDoCBQMuLYZC",
        "4ojIlQlez4Z7L3jTiasTVr"
      ],
      "artists_name": [
        "KOTONOHOUSE",
        "RANASOL"
      ]
    },
    {
      "uri": "spotify:track:4WRpB6AAn9F36NMvQSyUGn",
      "duration_ms": 239333,
      "isrc": "",
      "artists_id": [
        "3dkhk6RTgOerN0NQEmt8Nc"
      ],
      "artists_name": [
        "EVISBEATS"
      ]
    },
    {
      "uri": "spotify:track:4WZdUTYAUwMG63GCNA5jtk",
      "duration_ms": 308695,
      "isrc": "",
      "artists_id": [
        "7lbSsjYACZHn1MSDXPxNF2"
      ],
      "artists_name": [
        "Hikaru Utada"
      ]
    },
    {
      "uri": "spotify:track:4WZg0QN1i87wbtvHLxWssq",
      "duration_ms": 304187,
      "isrc": "",
      "artists_id": [
        "7lbSsjYACZHn1MSDXPxNF2"
      ],
      "artists_name": [
        "Hikaru Utada"
      ]
    },
    {
      "uri": "spotify:track:4Wa3KyBqrQ5GsKx5AUHd6d",
      "duration_ms": 295440,
      "isrc": "",
      "artists_id": [
        "7lbSsjYACZHn1MSDXPxNF2"
      ],
      "artists_name": [
        "Hikaru Utada"
      ]
    },
    {
      "uri": "spotify:track:4Wcymvo2Q5dnjAE7hk4sFP",
      "duration_ms": 435389,
      "isrc": "",
      "artists_id": [
        "6QBgbiQbOMwnieEzOd45XO",
        "6A5TcKOmRFkcUIgohM0Dmo"
      ],
      "artists_name": [
        "諸味胡瓜",
        "せんのいのり"
      ]
    },
    {
      "uri": "spotify:track:4Wr43xvsk9JWCzv0Bim6Ln",
      "duration_ms": 286173,
      "isrc": "",
      "artists_id": [
        "3VEG6gxFIMfl4Cdog26avS"
      ],
      "artists_name": [
        "Bill Evans Trio"
      ]
    },
    {
      "uri": "spotify:track:4WwE94tFdGIh26IiQxigIQ",
      "duration_ms": 71149,
      "isrc": "",
      "artists_id": [
        "67dtSHfEqrggSaOaicpaXq"
      ],
      "artists_name": [
        "水槽"
      ]
    },
    {
      "uri": "spotify:track:4X8NXYMWm1wlp1iIjFRoeq",
      "duration_ms": 356800,
      "isrc": "",
      "artists_id": [
        "0XraR5DqW6Vpp86omsB88K"
      ],
      "artists_name": [
        "kamome sano"
      ]
    },
    {
      "uri": "spotify:track:4XX5uZb9PvTKh8Nm2KSJfk",
      "duration_ms": 88966,
      "isrc": "",
      "artists_id": [
        "57DlMWmbVIf2ssJ8QBpBau"
      ],
      "artists_name": [
        "Toby Fox"
      ]
    },
    {
      "uri": "spotify:track:4Xeqd7RvHJzIOEVRwCa7sS",
      "duration_ms": 192052,
      "isrc": "",
      "artists_id": [
        "1oz1HYOyJhjshPi5Nvs3MX"
      ],
      "artists_name": [
        "IA"
      ]
    },
    {
      "uri": "spotify:track:4XvxzPArqlPD4wLOUvyNVr",
      "duration_ms": 272021,
      "isrc": "",
      "artists_id": [
        "7xgtCvgNymcpL81MiLpSmh"
      ],
      "artists_name": [
        "Pablo Garcia"
      ]
    },
    {
      "uri": "spotify:track:4Xx5GuQZ3YTC7fErN1Lcy0",
      "duration_ms": 153318,
      "isrc": "",
      "artists_id": [
        "6YbQDmSNnb9RxI3NMk4BN4",
        "65uuUPZ3mkqQ6gi0zfefHb"
      ],
      "artists_name": [
        "moreru",
        "Birds Fear Death"
      ]
    },
    {
      "uri": "spotify:track:4XxGTwKkbYkIfBQG7JyNVh",
      "duration_ms": 276573,
      "isrc": "",
      "artists_id": [
        "7lbSsjYACZHn1MSDXPxNF2"
      ],
      "artists_name": [
        "Hikaru Utada"
      ]
    },
    {
      "uri": "spotify:track:4Y0atVtZgiDgdlwJSAzYML",
      "duration_ms": 235138,
      "isrc": "",
      "artists_id": [
        "1oz1HYOyJhjshPi5Nvs3MX",
        "7os1UVlIK50EAaP990Z8aE"
      ],
      "artists_name": [
        "IA",
        "r-906"
      ]
    },
    {
      "uri": "spotify:track:4YNTytjcMLm61O3SkxMPJl",
      "duration_ms": 180892,
      "isrc": "",
      "artists_id": [
        "67dtSHfEqrggSaOaicpaXq"
      ],
      "artists_name": [
        "水槽"
      ]
    },
    {
      "uri": "spotify:track:4YQJePAs4XvOaPSq2byVGz",
      "duration_ms": 400000,
      "isrc": "",
      "artists_id": [
        "57DlMWmbVIf2ssJ8QBpBau",
        "6DGLXvs8Y2RO8VfdOpFLml",
        "5rIiXGQsgxh3nQhEpFIbx7"
      ],
      "artists_name": [
        "Toby Fox",
        "David Peacock",
        "Augustine Mayuga Gonzales"
      ]
    },
    {
      "uri": "spotify:track:4YendY7Q6DoZFetAtMhkaA",
      "duration_ms": 117135,
      "isrc": "",
      "artists_id": [
        "5QTu23XicMottOswlrdf5v",
        "1oz1HYOyJhjshPi5Nvs3MX"
      ],
      "artists_name": [
        "Der Wurm Blumchen",
        "IA"
      ]
    },
    {
      "uri": "spotify:track:4YmYWKM8uQdMWcoknDxgxZ",
      "duration_ms": 66346,
      "isrc": "",
      "artists_id": [
        "5bdiD2ANkGjawGUiBFYmRu",
        "33j8n8NVrlQtKnaAtIwLbE",
        "3tiDApDTEb1nT6hcy56Rza"
      ],
      "artists_name": [
        "lilbesh ramko",
        "piiandwai",
        "mohipoa"
      ]
    },
    {
      "uri": "spotify:track:4YrMeq6LEuRJPspoDXCSRw",
      "duration_ms": 196426,
      "isrc": "",
      "artists_id": [
        "3dkhk6RTgOerN0NQEmt8Nc"
      ],
      "artists_name": [
        "EVISBEATS"
      ]
    },
    {
      "uri": "spotify:track:4YrgPv1tsr5QckghkU8Z7W",
      "duration_ms": 297653,
      "isrc": "",
      "artists_id": [
        "5k3NfhEeZHpouIGDpjKOPo"
      ],
      "artists_name": [
        "Shiro SAGISU"
      ]
    },
    {
      "uri": "spotify:track:4Ywc3miiaaNFrLFrkEsfMA",
      "duration_ms": 261653,
      "isrc": "",
      "artists_id": [
        "0XraR5DqW6Vpp86omsB88K",
        "1whAPNHAalmyNIsfapcIcR"
      ],
      "artists_name": [
        "kamome sano",
        "Teto Kasane"
      ]
    },
    {
      "uri": "spotify:track:4ZFMitGdpEeK3kPT4X4c8J",
      "duration_ms": 202066,
      "isrc": "",
      "artists_id": [
        "57DlMWmbVIf2ssJ8QBpBau",
        "4tyZ8F1QPVTJ1EbkrlnpMd"
      ],
      "artists_name": [
        "Toby Fox",
        "String Player Gamer"
      ]
    },
    {
      "uri": "spotify:track:4ZHsFzpBYqtnwtKIQcHKHs",
      "duration_ms": 163366,
      "isrc": "",
      "artists_id": [
        "7LTiBdByoaUd329wCpmMcM",
        "0NU1ZwXIrwb0Kg7JZjWGyd",
        "7DkhW1MaKKLwJTSC5TtVW3",
        "7uugnrrGcHNunhme3bP1y3"
      ],
      "artists_name": [
        "MAISONdes",
        "ハローキティ",
        "なるみや",
        "Sasuke Haraguchi"
      ]
    },
    {
      "uri": "spotify:track:4ZMIYuiM4UlVRePiGIlgXT",
      "duration_ms": 416000,
      "isrc": "",
      "artists_id": [
        "3VEG6gxFIMfl4Cdog26avS"
      ],
      "artists_name": [
        "Bill Evans Trio"
      ]
    },
    {
      "uri": "spotify:track:4ZtM2lYJsDV9lp7CBt9oqu",
      "duration_ms": 291375,
      "isrc": "",
      "artists_id": [
        "4LZIZTkgDJt6JB2W8QdbXz"
      ],
      "artists_name": [
        "高峰伊織"
      ]
    },
    {
      "uri": "spotify:track:4a9xOJC6kgknv7cU4D99Ha",
      "duration_ms": 286613,
      "isrc": "",
      "artists_id": [
        "7lbSsjYACZHn1MSDXPxNF2"
      ],
      "artists_name": [
        "Hikaru Utada"
      ]
    },
    {
      "uri": "spotify:track:4aBu1tCQ2030MnINGXpvZS",
      "duration_ms": 381048,
      "isrc": "QZFYZ2052226",
      "artists_id": [
        "61YIW3A5JkcrOc57X3KEul"
      ],
      "artists_name": [
        "Yosan Getahun"
      ]
    },
    {
      "uri": "spotify:track:4aNxUQBEobtUH1v7YS8QQu",
      "duration_ms": 332773,
      "isrc": "JPE301401280",
      "artists_id": [
        "0Riv2KnFcLZA3JSVryRg4y"
      ],
      "artists_name": [
        "Hiroyuki Sawano"
      ]
    },
    {
      "uri": "spotify:track:4aOxxhBkt9uXPczGUQHPGI",
      "duration_ms": 126432,
      "isrc": "",
      "artists_id": [
        "141ww9EOPLPetF8mMt1gKF",
        "6KAgrAiCdJPDucMqR1kvMn"
      ],
      "artists_name": [
        "Yameii Online",
        "Deko"
      ]
    },
    {
      "uri": "spotify:track:4aWuzzIxtVPWtpTQwpI6tU",
      "duration_ms": 90613,
      "isrc": "",
      "artists_id": [
        "3dkhk6RTgOerN0NQEmt8Nc"
      ],
      "artists_name": [
        "EVISBEATS"
      ]
    },
    {
      "uri": "spotify:track:4acVqMPTvS0bq8H9znjqaG",
      "duration_ms": 252366,
      "isrc": "",
      "artists_id": [
        "0DBbtgOhLjX47Ml8bPWb0U"
      ],
      "artists_name": [
        "nyankobrq"
      ]
    },
    {
      "uri": "spotify:track:4asfbynajcQo9Y2FRaAyjc",
      "duration_ms": 255901,
      "isrc": "",
      "artists_id": [
        "7lbSsjYACZHn1MSDXPxNF2"
      ],
      "artists_name": [
        "Hikaru Utada"
      ]
    },
    {
      "uri": "spotify:track:4b0Sk3MKjbTFSyfl40xFea",
      "duration_ms": 248903,
      "isrc": "",
      "artists_id": [
        "7sDEXNgJzn0s6NtEsfFAMn"
      ],
      "artists_name": [
        "キツネDJ"
      ]
    },
    {
      "uri": "spotify:track:4b2Hl7uMSM88bXDzJAelfS",
      "duration_ms": 206900,
      "isrc": "",
      "artists_id": [
        "5k3NfhEeZHpouIGDpjKOPo"
      ],
      "artists_name": [
        "Shiro SAGISU"
      ]
    },
    {
      "uri": "spotify:track:4bBVT9yYCA9WYvRgxiyc0D",
      "duration_ms": 180291,
      "isrc": "",
      "artists_id": [
        "56f1j2OpB9qo7jFKL0hoL1"
      ],
      "artists_name": [
        "NF Zessho"
      ]
    },
    {
      "uri": "spotify:track:4bJ4WnWFV27wuGhUU0blpq",
      "duration_ms": 274586,
      "isrc": "",
      "artists_id": [
        "239OR3ZY9wKxFTrrDQHfkF"
      ],
      "artists_name": [
        "DEPAPEPE"
      ]
    },
    {
      "uri": "spotify:track:4bWKwdAZzKk3QxtzYSCLI8",
      "duration_ms": 345760,
      "isrc": "",
      "artists_id": [
        "3VEG6gxFIMfl4Cdog26avS"
      ],
      "artists_name": [
        "Bill Evans Trio"
      ]
    },
    {
      "uri": "spotify:track:4bbRv7IrwHHVEqMbdNyENu",
      "duration_ms": 328840,
      "isrc": "",
      "artists_id": [
        "7vd42XJxP9KO5LBY6d6lHv"
      ],
      "artists_name": [
        "Sylvia Mendez"
      ]
    },
    {
      "uri": "spotify:track:4bn18EWACtnepu20f2YtiA",
      "duration_ms": 237240,
      "isrc": "",
      "artists_id": [
        "7lbSsjYACZHn1MSDXPxNF2"
      ],
      "artists_name": [
        "Hikaru Utada"
      ]
    },
    {
      "uri": "spotify:track:4bri3GtQDN0FfCRxUotWST",
      "duration_ms": 219807,
      "isrc": "",
      "artists_id": [
        "7LNFEb2Axhj6CMHx3coSZc",
        "1oz1HYOyJhjshPi5Nvs3MX"
      ],
      "artists_name": [
        "gaburyu",
        "IA"
      ]
    },
    {
      "uri": "spotify:track:4c5hUMCHZpVtjPENJvFKua",
      "duration_ms": 182025,
      "isrc": "",
      "artists_id": [
        "1oz1HYOyJhjshPi5Nvs3MX",
        "2KpcAoYq2KiTAJXxx9hlEO"
      ],
      "artists_name": [
        "IA",
        "YASUHIRO"
      ]
    },
    {
      "uri": "spotify:track:4cBFjnFYjycw2EDWwZqdAP",
      "duration_ms": 481144,
      "isrc": "",
      "artists_id": [
        "7HfUJxeVTgrvhk0eWHFzV7"
      ],
      "artists_name": [
        "underscores"
      ]
    },
    {
      "uri": "spotify:track:4cQ2Rvxafj7g6hpOhDqw7B",
      "duration_ms": 126956,
      "isrc": "",
      "artists_id": [
        "1XVnuN1WPe1VMw78MuYeic"
      ],
      "artists_name": [
        "AssToro"
      ]
    },
    {
      "uri": "spotify:track:4cf4Ynu40Axx7ySLIv29u8",
      "duration_ms": 246000,
      "isrc": "",
      "artists_id": [
        "0XraR5DqW6Vpp86omsB88K"
      ],
      "artists_name": [
        "kamome sano"
      ]
    },
    {
      "uri": "spotify:track:4chNgeNqn81HD3WAeNkqXj",
      "duration_ms": 285373,
      "isrc": "",
      "artists_id": [
        "4MVyzYMgTwdP7Z49wAZHx0"
      ],
      "artists_name": [
        "Lynyrd Skynyrd"
      ]
    }
  ]
}